a_pandas_ex_fuzz/LICENSE
a_pandas_ex_fuzz/README.MD
a_pandas_ex_fuzz/__init__.py
a_pandas_ex_fuzz/requirements.txt
a_pandas_ex_fuzz/thirdparty.json
a_pandas_ex_fuzz-0.13.dist-info/LICENSE.rst
a_pandas_ex_fuzz-0.13.dist-info/METADATA
a_pandas_ex_fuzz-0.13.dist-info/WHEEL
a_pandas_ex_fuzz-0.13.dist-info/top_level.txt
a_pandas_ex_fuzz-0.13.dist-info/RECORD
