Metadata-Version: 2.1
Name: a-pandas-ex-fuzz
Version: 0.13
Summary: Intuitive way of using fuzz matching in pandas
Home-page: https://github.com/hansalemaos/a_pandas_ex_fuzz
Author: Johannes Fischer
Author-email: <aulasparticularesdealemaosp@gmail.com>
License: MIT
Keywords: debugger,debugging,fuzz,fuzzywuzzy
Classifier: Development Status :: 4 - Beta
Classifier: Programming Language :: Python :: 3 :: Only
Classifier: Programming Language :: Python :: 3.9
Classifier: Topic :: Scientific/Engineering :: Visualization
Classifier: Topic :: Software Development :: Libraries :: Python Modules
Classifier: Topic :: Text Editors :: Text Processing
Classifier: Topic :: Text Processing :: General
Classifier: Topic :: Text Processing :: Indexing
Classifier: Topic :: Text Processing :: Filters
Classifier: Topic :: Utilities
License-File: LICENSE.rst
Requires-Dist: a-pandas-ex-df-to-string
Requires-Dist: a-pandas-ex-plode-tool
Requires-Dist: fuzzywuzzy
Requires-Dist: pandas
Requires-Dist: rapidfuzz
